fastcraft/__init__.py
fastcraft/directory/create_dir.py
fastcraft/main.py
fastcraft-0.1.2.dist-info/entry_points.txt
fastcraft-0.1.2.dist-info/METADATA
fastcraft-0.1.2.dist-info/WHEEL
fastcraft-0.1.2.dist-info/RECORD
